data_finance/__init__.py
data_finance/vci.py
data_finance-1.0.0.dist-info/licenses/LICENSE
data_finance-1.0.0.dist-info/METADATA
data_finance-1.0.0.dist-info/WHEEL
data_finance-1.0.0.dist-info/top_level.txt
data_finance-1.0.0.dist-info/RECORD
